[
  {
    "title": " 新着ホットペッパーグルメ外食総研、今年度の忘年会･新年会の動向調査_概要編  (2025/12/17) ",
    "url": "https://gaisyoku.biz/news/33813/"
  },
  {
    "title": " 新着｢ファミリーマート｣限定！｢サッポロ 21時のレモネードサワー｣を順次発売  (2025/12/17) ",
    "url": "https://gaisyoku.biz/news/33812/"
  },
  {
    "title": " 新着ディップ、11月の全国アルバイト･パート平均時給は前年比45円増の1,360円  (2025/12/17) ",
    "url": "https://gaisyoku.biz/news/33811/"
  },
  {
    "title": " 新着大衆酒場きたぎん、対象店舗に｢きたぎん名物 小樽ザンギ食べ放題コース｣登場  (2025/12/17) ",
    "url": "https://gaisyoku.biz/news/33810/"
  },
  {
    "title": " 新着大阪王将、新業態｢東京都大阪王将市餃子特区｣を神田神保町にオープン  (2025/12/17) ",
    "url": "https://gaisyoku.biz/news/33809/"
  },
  {
    "title": " 新着なか卯、年越しの時期の定番商品｢鴨そば｣を今年も販売開始  (2025/12/17) ",
    "url": "https://gaisyoku.biz/news/33808/"
  },
  {
    "title": " 新着SANKO MARKETING FOODS、第1四半期(2025年7月～9月)の連結業績  (2025/12/17) ",
    "url": "https://gaisyoku.biz/news/33807/"
  },
  {
    "title": " 新着かんなん丸、第1四半期(2025年7月～9月)の業績を発表  (2025/12/17) ",
    "url": "https://gaisyoku.biz/news/33806/"
  },
  {
    "title": " 新着リクルートグループ、11月度三大都市圏アルバイト･パート募集時平均時給調査  (2025/12/16) ",
    "url": "https://gaisyoku.biz/news/33805/"
  },
  {
    "title": " 新着シングルヴィンヤードシリーズから｢長野古里カベルネ･ソーヴィニヨン2023｣登場  (2025/12/16) ",
    "url": "https://gaisyoku.biz/news/33804/"
  },
  {
    "title": " 新着帝国データバンク、食卓への影響度は？｢カレーライス物価指数｣調査_2025年10月  (2025/12/16) ",
    "url": "https://gaisyoku.biz/news/33803/"
  },
  {
    "title": " 新着パウス、｢日本のお酒と馬肉料理 うまえびす｣をリニューアルオープン  (2025/12/16) ",
    "url": "https://gaisyoku.biz/news/33802/"
  },
  {
    "title": " 新着デニーズ、13種類の追加トッピングで自分だけの一杯に！｢麻辣湯麺｣発売  (2025/12/16) ",
    "url": "https://gaisyoku.biz/news/33801/"
  },
  {
    "title": " 新着ベックスコーヒーショップ、一年の締めくくりに体も心も温まる褒美メニューを販売  (2025/12/16) ",
    "url": "https://gaisyoku.biz/news/33800/"
  },
  {
    "title": " 新着物語コーポレーション、第1四半期(2025年7月～9月)の連結業績を発表  (2025/12/16) ",
    "url": "https://gaisyoku.biz/news/33799/"
  },
  {
    "title": " 新着きちりホールディングス、第1四半期(2025年7月～9月)の連結業績を発表  (2025/12/16) ",
    "url": "https://gaisyoku.biz/news/33798/"
  },
  {
    "title": " 食品飲料業界10社による障害者同士の交流会｢エッキョウサミット｣を開催  (2025/12/15) ",
    "url": "https://gaisyoku.biz/news/33797/"
  },
  {
    "title": " じゃらんリサーチセンター、｢じゃらん人気温泉地ランキング2026｣を発表  (2025/12/15) ",
    "url": "https://gaisyoku.biz/news/33796/"
  },
  {
    "title": " 日本チェーンストア協会、広報担当者が選ぶ今年のチェーンストア10大ニュース  (2025/12/15) ",
    "url": "https://gaisyoku.biz/news/33795/"
  },
  {
    "title": " トリドールHD、従来の店長制度を刷新した｢ハピカンオフィサー制度｣の運用開始  (2025/12/15) ",
    "url": "https://gaisyoku.biz/news/33794/"
  }
]
