[
  {
    "title": " 新着もっと濃いレモン味に！｢サッポロ 濃いめのレモンサワー もっと濃いめ｣登場  (2026/04/22) ",
    "url": "https://gaisyoku.biz/news/34455/"
  },
  {
    "title": " 新着ぐるなびリサーチ部、2026年ゴールデンウィークの過ごし方に関する調査_後編  (2026/04/22) ",
    "url": "https://gaisyoku.biz/news/34454/"
  },
  {
    "title": " 新着観光庁、2026年1月～3月期のインバウンド消費動向調査結果(1次速報)  (2026/04/22) ",
    "url": "https://gaisyoku.biz/news/34453/"
  },
  {
    "title": " 新着都心にいながら緑豊かな非日常空間で楽しめる｢森のビアガーデン｣オープン  (2026/04/22) ",
    "url": "https://gaisyoku.biz/news/34452/"
  },
  {
    "title": " 新着とかち塚田、“旅”企画！｢世界を旅する新得地鶏 with 旅するスパイス｣を開始  (2026/04/22) ",
    "url": "https://gaisyoku.biz/news/34451/"
  },
  {
    "title": " 新着麦と卵、黄金色に輝く｢北海道産アスパラとミモレットの黄金ぺぺたま｣登場  (2026/04/22) ",
    "url": "https://gaisyoku.biz/news/34450/"
  },
  {
    "title": " 新着ユニシアホールディングス、第1四半期(2025年12月～2026年2月)の連結業績を発表  (2026/04/22) ",
    "url": "https://gaisyoku.biz/news/34449/"
  },
  {
    "title": " 新着ホリイフードサービス、第1四半期(2025年12月～2026年2月)の連結業績を発表  (2026/04/22) ",
    "url": "https://gaisyoku.biz/news/34448/"
  },
  {
    "title": " 新着普段は県内の飲食店でしか飲めない｢静岡麦酒(しずおかばくしゅ)｣を自宅でも  (2026/04/21) ",
    "url": "https://gaisyoku.biz/news/34447/"
  },
  {
    "title": " 新着ぐるなびリサーチ部、2026年ゴールデンウィークの過ごし方に関する調査  (2026/04/21) ",
    "url": "https://gaisyoku.biz/news/34446/"
  },
  {
    "title": " 新着日本フランチャイズチェーン協会、2026年3月度コンビニエンスストア統計調査  (2026/04/21) ",
    "url": "https://gaisyoku.biz/news/34445/"
  },
  {
    "title": " 新着イーストン、鶏白湯ラーメン専門店｢白鶏舎｣初の単独店を札幌市内にオープン  (2026/04/21) ",
    "url": "https://gaisyoku.biz/news/34444/"
  },
  {
    "title": " 新着やよい軒、人気中華2種を一つに！｢～四川風～麻婆茄子豆腐定食｣登場  (2026/04/21) ",
    "url": "https://gaisyoku.biz/news/34443/"
  },
  {
    "title": " 新着Korean Kitchen Shijan、パスチャーフェッドビーフの石焼ピビンバを販売  (2026/04/21) ",
    "url": "https://gaisyoku.biz/news/34442/"
  },
  {
    "title": " 新着大庄、中間期(2025年9月～2026年2月)の連結業績を発表  (2026/04/21) ",
    "url": "https://gaisyoku.biz/news/34441/"
  },
  {
    "title": " 新着SFPホールディングス、26年2月期(25年3月～26年2月)の連結業績を発表  (2026/04/21) ",
    "url": "https://gaisyoku.biz/news/34440/"
  },
  {
    "title": " プレミアム シングルモルト スコッチウイスキー｢ロイヤル･ブラックラ 25年｣発売  (2026/04/20) ",
    "url": "https://gaisyoku.biz/news/34439/"
  },
  {
    "title": " TableCheck、ダイナースクラブと提携して新しいグルメサービスを開始  (2026/04/20) ",
    "url": "https://gaisyoku.biz/news/34438/"
  },
  {
    "title": " 飲食向けPOSレジ｢POS＋ food｣が｢HANZO 自動発注｣と連携開始  (2026/04/20) ",
    "url": "https://gaisyoku.biz/news/34437/"
  },
  {
    "title": " カルビ一丁、焼肉店で本まぐろが食べ放題に！｢まぐろフェア｣を初めて開催  (2026/04/20) ",
    "url": "https://gaisyoku.biz/news/34436/"
  }
]
