[
  {
    "title": " 新着ワンダーテーブル、グルメイベント｢ワンダーテーブル レストランウィーク｣開催  (2026/07/13) ",
    "url": "https://gaisyoku.biz/news/34902/"
  },
  {
    "title": " 新着｢銀だこハイボール酒場｣から生まれた新ブランド｢銀だこ点心酒場｣登場  (2026/07/13) ",
    "url": "https://gaisyoku.biz/news/34901/"
  },
  {
    "title": " フレッシュネスバーガー、ハワイ気分を満喫！｢フレッシュネス･アロハフェス｣開催  (2026/07/11) ",
    "url": "https://gaisyoku.biz/news/34899/"
  },
  {
    "title": " ポッカサッポロ、そうめんのゆで湯に｢ポッカレモン１００｣添加でコシがアップ！  (2026/07/10) ",
    "url": "https://gaisyoku.biz/news/34898/"
  },
  {
    "title": " ぐるなび、都内3店舗で｢高機能バイオ炭｣を施用した｢枝豆｣の販売実証  (2026/07/10) ",
    "url": "https://gaisyoku.biz/news/34897/"
  },
  {
    "title": " 帝国データバンク、2026年上半期の全国企業倒産集計･分析結果を公表  (2026/07/10) ",
    "url": "https://gaisyoku.biz/news/34896/"
  },
  {
    "title": " 赤から、食欲そそる夏季限定ランチ！3種類から選べる｢冷麺ランチ｣登場  (2026/07/10) ",
    "url": "https://gaisyoku.biz/news/34895/"
  },
  {
    "title": " 60周年を迎える｢木曽路｣の新提案！｢焼きしゃぶ｣が登場  (2026/07/10) ",
    "url": "https://gaisyoku.biz/news/34894/"
  },
  {
    "title": " つじ田、アークヒルズで開催される｢夏の激辛グランプリ2026｣に参戦  (2026/07/10) ",
    "url": "https://gaisyoku.biz/news/34893/"
  },
  {
    "title": " 吉野家ホールディングス、第1四半期(2026年3月～5月)の連結業績を発表  (2026/07/10) ",
    "url": "https://gaisyoku.biz/news/34892/"
  },
  {
    "title": " ハイデイ日高、第1四半期(2026年3月～5月)の業績を発表  (2026/07/10) ",
    "url": "https://gaisyoku.biz/news/34891/"
  },
  {
    "title": " YEBISU BREWERY TOKYO、数量限定ビール｢涼音の華やぎ｣を販売  (2026/07/09) ",
    "url": "https://gaisyoku.biz/news/34890/"
  },
  {
    "title": " 高評価を得たパンの名店TOP100！｢食べログ パン 百名店 2026｣  (2026/07/09) ",
    "url": "https://gaisyoku.biz/news/34889/"
  },
  {
    "title": " 帝国データバンク、｢すし店｣の倒産動向(2026年1～6月)を公表  (2026/07/09) ",
    "url": "https://gaisyoku.biz/news/34888/"
  },
  {
    "title": " 浅野屋、｢ベアレン醸造所×浅野屋 Bread　Weizen｣発売  (2026/07/09) ",
    "url": "https://gaisyoku.biz/news/34887/"
  },
  {
    "title": " 焼肉きんぐ、今年の夏はハワイ気分を味わえる！｢ハワイフェア｣を初開催  (2026/07/09) ",
    "url": "https://gaisyoku.biz/news/34886/"
  },
  {
    "title": " bb.q オリーブチキン、｢骨なしモモ黄金フライドチキン｣をおトクに楽しめる！  (2026/07/09) ",
    "url": "https://gaisyoku.biz/news/34885/"
  },
  {
    "title": " あみやき亭、第1四半期(2026年4月～7月)の連結業績を発表  (2026/07/09) ",
    "url": "https://gaisyoku.biz/news/34884/"
  },
  {
    "title": " カルラ、第1四半期(2026年3月～5月)の連結業績を発表  (2026/07/09) ",
    "url": "https://gaisyoku.biz/news/34883/"
  },
  {
    "title": " 北海道を応援！｢サッポロ クラシック ゴールデンカムイデザイン缶｣を発売  (2026/07/08) ",
    "url": "https://gaisyoku.biz/news/34882/"
  }
]
