[
  {
    "title": " 2026/02/26 欧米豪・訪日外国人旅行者の「日本の美容サロン」利用に関する実態調査～利用率は4割超、支出は2万円超。「清潔感」と「技術」がカギ～ 調査・研究 ",
    "url": "https://hba.beauty.hotpepper.jp/search/overseas/74787/"
  },
  {
    "title": " 2026/02/25 20代接客はどうしたらいい？SNS世代の本音とは？ 調査・研究 ",
    "url": "https://hba.beauty.hotpepper.jp/search/column/c_zgene/75010/"
  },
  {
    "title": " 2026/02/25 栃木エステサロンで未経験ママを採用！正社員登用した理由とは？ 連載記事 ",
    "url": "https://hba.beauty.hotpepper.jp/check/74694/"
  },
  {
    "title": " 2026/02/24 【速報】HOT PEPPER Beauty AWARD 2026 スタイル部門・サロン部門を発表！ 連載記事 ",
    "url": "https://hba.beauty.hotpepper.jp/check/75399/"
  },
  {
    "title": " 2026/02/09 高知ヘアサロンでアシスタントを採用！求める人材と出会えた理由とは？ 連載記事 ",
    "url": "https://hba.beauty.hotpepper.jp/check/73812/"
  },
  {
    "title": " 2026/02/06 熟練のシュガーリング脱毛×素材にこだわる黄土ローズ蒸し。希少性の高い個人サロンで圧倒的集客を実現。 連載記事 ",
    "url": "https://hba.beauty.hotpepper.jp/check/74728/"
  },
  {
    "title": " 2026/02/02 数字で見る美容業界【2026年1月】美容消費データを更新 調査・研究 ",
    "url": "https://hba.beauty.hotpepper.jp/search_sp/"
  },
  {
    "title": " 2026/01/30 男性客は「時短」だけじゃない。調査で判明！「30代の疲労・抜け毛」の悩みと「20代の新メニュー」ニーズとは？ 調査・研究 ",
    "url": "https://hba.beauty.hotpepper.jp/search/column/c_price/74946/"
  },
  {
    "title": " 2026/01/30 ファイブスター 佐久間 正之/新卒給与25万円、次は賃金1.5倍!?経営のプロが挑む業界の構造改革。 連載記事 ",
    "url": "https://hba.beauty.hotpepper.jp/check/74819/"
  },
  {
    "title": " 2026/01/30 「癒やし」だけじゃない!?オトナ女性の「眼精疲労」「髪のうねり」にヘッドスパ提案 調査・研究 ",
    "url": "https://hba.beauty.hotpepper.jp/search/column/c_price/74867/"
  },
  {
    "title": " 2026/01/29 たった5分で単価UP!?冬のヘッドスパ活用術 ～「話題のアレ、やってみたい」を逃さない！～ 調査・研究 ",
    "url": "https://hba.beauty.hotpepper.jp/search/column/c_price/74790/"
  },
  {
    "title": " 2026/01/29 頭皮ケアメニューに関する調査 調査・研究 ",
    "url": "https://hba.beauty.hotpepper.jp/search/trade/hair/price/74807/"
  },
  {
    "title": " 2026/01/28 名古屋の整体院で有望スタッフを採用！育成のこだわりとは？ 連載記事 ",
    "url": "https://hba.beauty.hotpepper.jp/check/73364/"
  },
  {
    "title": " 2026/01/23 宮崎ヘアサロンで3名採用！女性が長く働けるサロンとは？ 連載記事 ",
    "url": "https://hba.beauty.hotpepper.jp/check/73588/"
  },
  {
    "title": " 2026/01/22 ハーブピーリングNOBLE新宿/「人間力」と「データ分析」を武器にロジカルかつ誠実なサロン運営。 連載記事 ",
    "url": "https://hba.beauty.hotpepper.jp/check/73814/"
  }
]
